[
  {
    "profile": "Consumption",
    "scale_target": 1,
    "run_id": "consumption-n1-r1-20260614-143834",
    "file": "consumption-scale-1-run-1.jsonl",
    "samples": 6,
    "unique_replicas": 1,
    "unique_boot_ids": 1,
    "boot_time_clusters": 1,
    "cluster_centers_ms": [
      1781445672601
    ],
    "hit_ratio": 1.0
  },
  {
    "profile": "Consumption",
    "scale_target": 10,
    "run_id": "consumption-n10-r1-20260614-144055",
    "file": "consumption-scale-10-run-1.jsonl",
    "samples": 80,
    "unique_replicas": 10,
    "unique_boot_ids": 10,
    "boot_time_clusters": 10,
    "cluster_centers_ms": [
      1781437557979,
      1781440752255,
      1781444029442,
      1781444891545,
      1781445734274,
      1781445771025,
      1781447835915,
      1781447970264,
      1781447979918,
      1781448022698
    ],
    "hit_ratio": 1.0
  },
  {
    "profile": "Consumption",
    "scale_target": 3,
    "run_id": "consumption-n3-r1-20260614-143915",
    "file": "consumption-scale-3-run-1.jsonl",
    "samples": 30,
    "unique_replicas": 3,
    "unique_boot_ids": 3,
    "boot_time_clusters": 3,
    "cluster_centers_ms": [
      1781441260369,
      1781447713105,
      1781447845838
    ],
    "hit_ratio": 1.0
  },
  {
    "profile": "Consumption",
    "scale_target": 30,
    "run_id": "consumption-n30-r1-20260614-144240",
    "file": "consumption-scale-30-run-1.jsonl",
    "samples": 240,
    "unique_replicas": 30,
    "unique_boot_ids": 30,
    "boot_time_clusters": 27,
    "cluster_centers_ms": [
      1781224393764,
      1781422256604,
      1781425138542,
      1781426976931,
      1781435562053,
      1781438580396,
      1781439015719,
      1781439759111,
      1781440738168,
      1781440752345,
      1781446038247,
      1781446056668,
      1781447133469,
      1781447372820,
      1781447432535,
      1781447457839,
      1781447577210,
      1781447732944,
      1781447838938,
      1781447857646,
      1781447904024,
      1781447916412,
      1781447997915,
      1781448048040,
      1781448060500,
      1781448085848,
      1781448097627
    ],
    "hit_ratio": 1.0
  },
  {
    "profile": "Consumption",
    "scale_target": 30,
    "run_id": "consumption-n30-r2-20260614-144448",
    "file": "consumption-scale-30-run-2.jsonl",
    "samples": 240,
    "unique_replicas": 30,
    "unique_boot_ids": 30,
    "boot_time_clusters": 27,
    "cluster_centers_ms": [
      1781224393763,
      1781422256607,
      1781425138541,
      1781426976928,
      1781435562051,
      1781438580395,
      1781439015720,
      1781439759113,
      1781440738509,
      1781440752348,
      1781446038248,
      1781446056665,
      1781447133471,
      1781447372821,
      1781447432538,
      1781447457839,
      1781447577210,
      1781447732946,
      1781447838936,
      1781447857646,
      1781447904024,
      1781447916412,
      1781447997918,
      1781448048038,
      1781448060502,
      1781448085782,
      1781448097626
    ],
    "hit_ratio": 1.0
  },
  {
    "profile": "Consumption",
    "scale_target": 30,
    "run_id": "consumption-n30-r3-20260614-144548",
    "file": "consumption-scale-30-run-3.jsonl",
    "samples": 240,
    "unique_replicas": 30,
    "unique_boot_ids": 30,
    "boot_time_clusters": 27,
    "cluster_centers_ms": [
      1781224393763,
      1781422256605,
      1781425138542,
      1781426976930,
      1781435562051,
      1781438580395,
      1781439015720,
      1781439759111,
      1781440738374,
      1781440752347,
      1781446038251,
      1781446056669,
      1781447133470,
      1781447372820,
      1781447432537,
      1781447457839,
      1781447577208,
      1781447732943,
      1781447838936,
      1781447857647,
      1781447904024,
      1781447916411,
      1781447997917,
      1781448048038,
      1781448060501,
      1781448085784,
      1781448097625
    ],
    "hit_ratio": 1.0
  },
  {
    "profile": "Dedicated-D8",
    "scale_target": 1,
    "run_id": "dedicated-d8-n1-r1-20260614-144648",
    "file": "dedicated-d8-scale-1-run-1.jsonl",
    "samples": 6,
    "unique_replicas": 1,
    "unique_boot_ids": 1,
    "boot_time_clusters": 1,
    "cluster_centers_ms": [
      1781447475863
    ],
    "hit_ratio": 1.0
  },
  {
    "profile": "Dedicated-D8",
    "scale_target": 10,
    "run_id": "dedicated-d8-n10-r1-20260614-144853",
    "file": "dedicated-d8-scale-10-run-1.jsonl",
    "samples": 80,
    "unique_replicas": 10,
    "unique_boot_ids": 1,
    "boot_time_clusters": 1,
    "cluster_centers_ms": [
      1781447475864
    ],
    "hit_ratio": 1.0
  },
  {
    "profile": "Dedicated-D8",
    "scale_target": 10,
    "run_id": "dedicated-d8-n10-r2-20260614-145035",
    "file": "dedicated-d8-scale-10-run-2.jsonl",
    "samples": 80,
    "unique_replicas": 10,
    "unique_boot_ids": 1,
    "boot_time_clusters": 1,
    "cluster_centers_ms": [
      1781447475864
    ],
    "hit_ratio": 1.0
  },
  {
    "profile": "Dedicated-D8",
    "scale_target": 10,
    "run_id": "dedicated-d8-n10-r3-20260614-145121",
    "file": "dedicated-d8-scale-10-run-3.jsonl",
    "samples": 80,
    "unique_replicas": 10,
    "unique_boot_ids": 1,
    "boot_time_clusters": 1,
    "cluster_centers_ms": [
      1781447475864
    ],
    "hit_ratio": 1.0
  },
  {
    "profile": "Dedicated-D8",
    "scale_target": 3,
    "run_id": "dedicated-d8-n3-r1-20260614-144728",
    "file": "dedicated-d8-scale-3-run-1.jsonl",
    "samples": 30,
    "unique_replicas": 3,
    "unique_boot_ids": 1,
    "boot_time_clusters": 1,
    "cluster_centers_ms": [
      1781447475865
    ],
    "hit_ratio": 1.0
  }
]